utal/__init__.py
utal/client.py
utal/conversation.py
utal/core.py
utal/exceptions.py
utal/messages.py
utal/page.py
utal-0.3.0.dist-info/LICENSE
utal-0.3.0.dist-info/METADATA
utal-0.3.0.dist-info/WHEEL
utal-0.3.0.dist-info/top_level.txt
utal-0.3.0.dist-info/RECORD
