Metadata-Version: 2.2
Name: utal
Version: 0.3.0
Summary: Unnoficial TikTok library for chatbot making. Use at your own risk.
Home-page: https://github.com/thiagostilo2121/utal
Author: Thiago Valentín Stilo Limarino
Author-email: stilothiagovalentin@gmail.com
Classifier: Programming Language :: Python :: 3
Classifier: License :: OSI Approved :: MIT License
Classifier: Operating System :: OS Independent
Requires-Python: >=3.9
License-File: LICENSE
Requires-Dist: selenium==4.29.0
Dynamic: author
Dynamic: author-email
Dynamic: classifier
Dynamic: description
Dynamic: description-content-type
Dynamic: home-page
Dynamic: requires-dist
Dynamic: requires-python
Dynamic: summary
